{
  "ignorePaths": [
    "**/node_modules/**",
    "**/vscode-extension/**",
    "**/.git/**",
    "**/.pnpm-lock.json",
    ".vscode",
    "package-lock.json",
    "megalinter-reports",
    "bun.lockb"
  ],
  "useGitignore": true,
  "allowCompoundWords": true,
  "language": "en,en-AU,en-BZ,en-CA,en-CB,en-GB,en-IE,en-JM,en-NZ,en-PH,en-TT,en-US,en-ZA,en-ZW",
  "version": "0.2",
  "words": [
    "bannable",
    "codeql",
    "colorette",
    "Currin",
    "dbaeumer",
    "delims",
    "dhoeric",
    "dpaste",
    "eamodio",
    "emojify",
    "esbenp",
    "evondev",
    "exiasr",
    "hadolint",
    "ianvs",
    "joshuanianji",
    "keyid",
    "lockb",
    "Mihir",
    "mrdgh",
    "npmrc",
    "ohwmr",
    "Rabade",
    "regist",
    "sapphirejs",
    "sapphirerc",
    "scanjs",
    "shfmt",
    "shyim",
    "sonarjs",
    "spmeesseman",
    "stefanzweifel",
    "tsbuildinfo",
    "usebackq",
    "usernamehw",
    "venv",
    "wdhongtw",
    "yaspr"
  ]
}
